fingoti/__init__.py
fingoti/api_client.py
fingoti/configuration.py
fingoti/exceptions.py
fingoti/model_utils.py
fingoti/rest.py
fingoti/api/__init__.py
fingoti/api/device_api.py
fingoti/api/followings_api.py
fingoti/api/organisation_api.py
fingoti/api/report_api.py
fingoti/api/user_api.py
fingoti/api/webhook_api.py
fingoti/apis/__init__.py
fingoti/command/__init__.py
fingoti/command/builder.py
fingoti/command/enums.py
fingoti/command/models.py
fingoti/command/device/__init__.py
fingoti/command/device/device_activity.py
fingoti/command/device/device_blink.py
fingoti/command/device/device_bus.py
fingoti/command/device/device_colour.py
fingoti/command/device/device_information.py
fingoti/command/device/device_poke.py
fingoti/command/device/device_power.py
fingoti/command/device/device_sleep.py
fingoti/command/device/device_time.py
fingoti/command/device/device_uptime.py
fingoti/command/device/device_version.py
fingoti/model/__init__.py
fingoti/model/add_address_request.py
fingoti/model/add_follow_dto.py
fingoti/model/add_preset_request.py
fingoti/model/add_preset_result.py
fingoti/model/add_role_request.py
fingoti/model/add_webhook_dto.py
fingoti/model/add_webhook_result.py
fingoti/model/all_webhooks_dto.py
fingoti/model/azure_message.py
fingoti/model/azure_message_content.py
fingoti/model/call_log_dto.py
fingoti/model/claim_request.py
fingoti/model/claim_result.py
fingoti/model/claimed_device_response.py
fingoti/model/claimed_devices_dto.py
fingoti/model/cloud_reason.py
fingoti/model/command_direction.py
fingoti/model/command_log_response.py
fingoti/model/data_log_response.py
fingoti/model/default.py
fingoti/model/default_with_id.py
fingoti/model/default_with_token.py
fingoti/model/device_blink.py
fingoti/model/device_bus.py
fingoti/model/device_cloud.py
fingoti/model/device_location.py
fingoti/model/device_nodes_response.py
fingoti/model/device_pebl_dto.py
fingoti/model/device_power.py
fingoti/model/device_request.py
fingoti/model/device_session.py
fingoti_sdk-1.0.0.dist-info/METADATA
fingoti_sdk-1.0.0.dist-info/WHEEL
fingoti_sdk-1.0.0.dist-info/top_level.txt
fingoti_sdk-1.0.0.dist-info/RECORD
