Metadata-Version: 2.1
Name: fingoti-sdk
Version: 1.0.0
Summary: Fingoti SDK
Home-page: https://github.com/fingoti/sdk-python
Author: Fingoti Team
Author-email: support@fingoti.com
Keywords: Fingoti,Fingoti SDK,Fingoti API,IoT,Pebl
Requires-Python: >=3.6
Requires-Dist: urllib3 (>=1.25.3)
Requires-Dist: python-dateutil
